[
  {
    "class": "CANCEL",
    "doc_url": "https://www.release.tdnet.info/inbs/140120260512525786.pdf",
    "enriched_at": "2026-05-20T15:09:05+09:00",
    "enrichment_method": "tier_b_regex",
    "id": "TDnet-140120260512525786",
    "key_facts": {
      "shares": 9700000
    },
    "name_en": "KUREHA CORPORATION",
    "name_jp": "クレハ",
    "profile_url": null,
    "signal_score": 1,
    "source": "TDnet",
    "summary_en": "",
    "summary_jp": "",
    "tag": "Cancellation · size TBC",
    "tag_en": "Cancellation · 9,700,000 shares",
    "tag_jp": "自己株式消却 ・ 9,700,000株",
    "ticker": "4023",
    "ts": "2026-05-12T15:30:00+09:00"
  }
]
