[
  {
    "class": "DIV",
    "doc_url": "https://www.release.tdnet.info/inbs/140120260514535454.pdf",
    "id": "TDnet-140120260514535454",
    "name_en": "大日精化",
    "name_jp": "大日精化",
    "profile_url": null,
    "source": "TDnet",
    "summary_en": "大日精化 announced a material dividend change (dividend hike). Reframes the return-of-capital baseline.",
    "summary_jp": "大日精化が配当方針変更を開示（増配）。資本還元基準が刷新。",
    "tag": "Dividend · dividend hike",
    "ticker": "4116",
    "ts": "2026-05-15T14:30:00+09:00"
  }
]
