[
  {
    "class": "MBO",
    "doc_url": "https://www.release.tdnet.info/inbs/140120260421507226.pdf",
    "id": "TDnet-140120260421507226",
    "name_en": "インフロニアＨＤ",
    "name_jp": "インフロニアＨＤ",
    "profile_url": null,
    "source": "TDnet",
    "summary_en": "Tender offer disclosed for インフロニアＨＤ. Take-private transaction removes the float and resets capital policy.",
    "summary_jp": "インフロニアＨＤに対する公開買付を開示。非公開化により資本政策が再構築。",
    "tag": "Tender offer",
    "ticker": "5076",
    "ts": "2026-04-22T15:30:00+09:00"
  },
  {
    "class": "MBO",
    "doc_url": "https://www.release.tdnet.info/inbs/140120260413502654.pdf",
    "id": "TDnet-140120260413502654",
    "name_en": "インフロニアＨＤ",
    "name_jp": "インフロニアＨＤ",
    "profile_url": null,
    "source": "TDnet",
    "summary_en": "Going-private (parent) disclosed for インフロニアＨＤ. Take-private transaction removes the float and resets capital policy.",
    "summary_jp": "インフロニアＨＤに対する完全子会社化を開示。非公開化により資本政策が再構築。",
    "tag": "Going-private (parent)",
    "ticker": "5076",
    "ts": "2026-04-14T14:30:00+09:00"
  }
]
