[
  {
    "class": "BUYBACK",
    "doc_url": "https://www.release.tdnet.info/inbs/140120260501516534.pdf",
    "id": "TDnet-140120260501516534",
    "name_en": "ブリヂス",
    "name_jp": "ブリヂス",
    "profile_url": null,
    "source": "TDnet",
    "summary_en": "ブリヂス authorised a share buyback. Direct return of capital and a signal management views shares as undervalued.",
    "summary_jp": "ブリヂスが自己株式取得を決議。資本還元と株価評価のシグナル。",
    "tag": "Buyback · size TBC",
    "ticker": "5108",
    "ts": "2026-05-07T15:30:00+09:00"
  }
]
