[
  {
    "class": "BUYBACK",
    "doc_url": "https://www.release.tdnet.info/inbs/140120260511521805.pdf",
    "enriched_at": "2026-05-20T15:09:29+09:00",
    "enrichment_method": "tier_b_regex",
    "id": "TDnet-140120260511521805",
    "key_facts": {
      "method": "Open-market",
      "pct_so": 1.22,
      "shares": 2300000
    },
    "name_en": "NICHIAS CORPORATION",
    "name_jp": "ニチアス",
    "profile_url": null,
    "source": "TDnet",
    "summary_en": "ニチアス authorized a share buyback. Direct return of capital and a signal management views shares as undervalued.",
    "summary_jp": "ニチアスが自己株式取得を決議。資本還元と株価評価のシグナル。",
    "tag": "Buyback · size TBC",
    "tag_en": "Buyback · 2,300,000 shares (1.22% S/O) · Open-market",
    "tag_jp": "自社株買い ・ 2,300,000株 (発行済1.22%) ・ Open-market",
    "ticker": "5393",
    "ts": "2026-05-11T15:30:00+09:00"
  }
]
