[
  {
    "class": "DIV",
    "doc_url": "https://www.release.tdnet.info/inbs/140120260513530038.pdf",
    "id": "TDnet-140120260513530038",
    "name_en": "ＣＫサンエツ",
    "name_jp": "ＣＫサンエツ",
    "profile_url": null,
    "source": "TDnet",
    "summary_en": "ＣＫサンエツ announced a material dividend change (progressive policy). Reframes the return-of-capital baseline.",
    "summary_jp": "ＣＫサンエツが配当方針変更を開示（累進配当方針）。資本還元基準が刷新。",
    "tag": "Dividend · progressive policy",
    "ticker": "5757",
    "ts": "2026-05-13T15:30:00+09:00"
  }
]
