[
  {
    "class": "COC_INITIAL",
    "doc_url": "https://www.release.tdnet.info/inbs/140120260514532466.pdf",
    "enriched_at": "2026-05-20T15:08:09+09:00",
    "enrichment_method": "tier_b_regex",
    "id": "TDnet-140120260514532466",
    "key_facts": {},
    "name_en": "FUJISASH CO.,LTD.",
    "name_jp": "不二サッシ",
    "profile_url": null,
    "signal_score": 3,
    "source": "TDnet",
    "summary_en": "",
    "summary_jp": "",
    "tag": "Cost-of-capital · update",
    "tag_en": "Cost-of-capital",
    "tag_jp": "資本コスト経営",
    "ticker": "5940",
    "ts": "2026-05-14T14:00:00+09:00"
  }
]
