[
  {
    "class": "DIV_HIKE",
    "doc_url": "https://www.release.tdnet.info/inbs/140120260427511584.pdf",
    "enriched_at": "2026-05-20T15:11:21+09:00",
    "enrichment_method": "tier_b_regex",
    "id": "TDnet-140120260427511584",
    "key_facts": {
      "div_new": 320,
      "div_old": 160
    },
    "name_en": "T.RAD Co., Ltd.",
    "name_jp": "ティラド",
    "profile_url": null,
    "signal_score": 2,
    "source": "TDnet",
    "summary_en": "",
    "summary_jp": "",
    "tag": "Dividend · dividend hike",
    "tag_en": "Dividend · ¥160 → ¥320 (+100%)",
    "tag_jp": "配当 ・ ¥160 → ¥320",
    "ticker": "7236",
    "ts": "2026-04-27T16:00:00+09:00"
  }
]
