[
  {
    "class": "DIV",
    "doc_url": "https://www.release.tdnet.info/inbs/140120260401596821.pdf",
    "id": "TDnet-140120260401596821",
    "name_en": "Ｇ－ＴＷＯＳＴＯＮＥ",
    "name_jp": "Ｇ－ＴＷＯＳＴＯＮＥ",
    "profile_url": null,
    "source": "TDnet",
    "summary_en": "Ｇ－ＴＷＯＳＴＯＮＥ announced a material dividend change (dividend hike). Reframes the return-of-capital baseline.",
    "summary_jp": "Ｇ－ＴＷＯＳＴＯＮＥが配当方針変更を開示（増配）。資本還元基準が刷新。",
    "tag": "Dividend · dividend hike",
    "ticker": "7352",
    "ts": "2026-04-14T15:30:00+09:00"
  }
]
