[
  {
    "class": "DIV",
    "doc_url": "https://www.release.tdnet.info/inbs/140120260403598202.pdf",
    "enriched_at": "2026-05-20T15:12:13+09:00",
    "enrichment_method": "tier_b_regex",
    "id": "TDnet-140120260403598202",
    "key_facts": {},
    "name_en": "TSUTSUMI JEWELRY CO.,LTD.",
    "name_jp": "ツツミ",
    "profile_url": null,
    "source": "TDnet",
    "summary_en": "ツツミ announced a material dividend change (dividend hike). Reframes the return-of-capital baseline.",
    "summary_jp": "ツツミが配当方針変更を開示（増配）。資本還元基準が刷新。",
    "tag": "Dividend · dividend hike",
    "tag_en": "Dividend · details pending",
    "tag_jp": "配当方針・詳細確認中",
    "ticker": "7937",
    "ts": "2026-04-13T14:00:00+09:00"
  }
]
