[
  {
    "class": "BUYBACK",
    "doc_url": "https://www.release.tdnet.info/inbs/140120260513529725.pdf",
    "id": "TDnet-140120260513529725",
    "name_en": "タキヒヨー",
    "name_jp": "タキヒヨー",
    "profile_url": null,
    "source": "TDnet",
    "summary_en": "タキヒヨー authorized a share buyback. Direct return of capital and a signal management views shares as undervalued.",
    "summary_jp": "タキヒヨーが自己株式取得を決議。資本還元と株価評価のシグナル。",
    "tag": "Buyback · size TBC",
    "ticker": "9982",
    "ts": "2026-05-13T14:30:00+09:00"
  }
]
